odoo/addons/l10n_it_edi_related_document/README.rst
odoo/addons/l10n_it_edi_related_document/__init__.py
odoo/addons/l10n_it_edi_related_document/__manifest__.py
odoo/addons/l10n_it_edi_related_document/data/invoice_it_template.xml
odoo/addons/l10n_it_edi_related_document/i18n/it.po
odoo/addons/l10n_it_edi_related_document/i18n/l10n_it_edi_related_document.pot
odoo/addons/l10n_it_edi_related_document/models/__init__.py
odoo/addons/l10n_it_edi_related_document/models/account_move.py
odoo/addons/l10n_it_edi_related_document/models/account_move_line.py
odoo/addons/l10n_it_edi_related_document/readme/CONTRIBUTORS.md
odoo/addons/l10n_it_edi_related_document/readme/DESCRIPTION.md
odoo/addons/l10n_it_edi_related_document/security/ir.model.access.csv
odoo/addons/l10n_it_edi_related_document/static/description/icon.png
odoo/addons/l10n_it_edi_related_document/static/description/index.html
odoo/addons/l10n_it_edi_related_document/tests/__init__.py
odoo/addons/l10n_it_edi_related_document/tests/test_import_xml.py
odoo/addons/l10n_it_edi_related_document/tests/import_xmls/IT01234567888_FPR01_02.xml
odoo/addons/l10n_it_edi_related_document/views/account_move_related_documents.xml
odoo/addons/l10n_it_edi_related_document/views/l10n_it_views.xml
odoo/addons/l10n_it_edi_related_document/views/related_document_views.xml
odoo_addon_l10n_it_edi_related_document-18.0.1.0.0.5.dist-info/METADATA
odoo_addon_l10n_it_edi_related_document-18.0.1.0.0.5.dist-info/WHEEL
odoo_addon_l10n_it_edi_related_document-18.0.1.0.0.5.dist-info/top_level.txt
odoo_addon_l10n_it_edi_related_document-18.0.1.0.0.5.dist-info/RECORD
